rescape_graphene/__init__.py
rescape_graphene/schema.py
rescape_graphene/testcases.py
rescape_graphene/django_helpers/__init__.py
rescape_graphene/django_helpers/pagination.py
rescape_graphene/django_helpers/test_write_helpers.py
rescape_graphene/django_helpers/versioning.py
rescape_graphene/django_helpers/write_helpers.py
rescape_graphene/graphql_helpers/__init__.py
rescape_graphene/graphql_helpers/exceptions.py
rescape_graphene/graphql_helpers/graphene_helpers.py
rescape_graphene/graphql_helpers/json_field_helpers.py
rescape_graphene/graphql_helpers/middleware.py
rescape_graphene/graphql_helpers/mutate_related_helpers.py
rescape_graphene/graphql_helpers/schema_helpers.py
rescape_graphene/graphql_helpers/schema_validating_helpers.py
rescape_graphene/graphql_helpers/str_converters.py
rescape_graphene/graphql_helpers/test_graphene_helpers.py
rescape_graphene/graphql_helpers/test_schema_helpers.py
rescape_graphene/graphql_helpers/views.py
rescape_graphene/graphql_helpers/snapshots/__init__.py
rescape_graphene/schema_models/__init__.py
rescape_graphene/schema_models/django_object_type_revisioned_mixin.py
rescape_graphene/schema_models/group_schema.py
rescape_graphene/schema_models/parameters_type.py
rescape_graphene/schema_models/test_paramters_type.py
rescape_graphene/schema_models/token_graphql.py
rescape_graphene/schema_models/token_schema.py
rescape_graphene/schema_models/user_schema.py
rescape_graphene/schema_models/user_schema_test.py
rescape_graphene/schema_models/geojson/__init__.py
rescape_graphene/schema_models/geojson/converters.py
rescape_graphene/schema_models/geojson/test_converters.py
rescape_graphene/schema_models/geojson/test_serializers.py
rescape_graphene/schema_models/geojson/types/__init__.py
rescape_graphene/schema_models/geojson/types/feature_collection.py
rescape_graphene/schema_models/geojson/types/geojson_data_schema.py
rescape_graphene/schema_models/geojson/types/geometry.py
rescape_graphene/schema_models/snapshots/__init__.py
rescape_graphene-0.4.19.dist-info/LICENSE
rescape_graphene-0.4.19.dist-info/METADATA
rescape_graphene-0.4.19.dist-info/WHEEL
rescape_graphene-0.4.19.dist-info/top_level.txt
rescape_graphene-0.4.19.dist-info/RECORD
