Metadata-Version: 2.1
Name: rescape-graphene
Version: 0.4.19
Summary: Graphene helpers for rescape projects
Home-page: https://github.com/calocan/rescape_graphene
Author: Andy Likuski
Author-email: andy@likuski.org
License: UNKNOWN
Platform: UNKNOWN
Classifier: Programming Language :: Python :: 3
Classifier: License :: OSI Approved :: MIT License
Classifier: Operating System :: OS Independent
License-File: LICENSE
Requires-Dist: pyramda
Requires-Dist: graphene
Requires-Dist: graphene-django
Requires-Dist: inflection
Requires-Dist: deepmerge
Requires-Dist: djangorestframework
Requires-Dist: djangorestframework-jwt
Requires-Dist: psycopg2-binary
Requires-Dist: django-graphql-jwt
Requires-Dist: utils
Requires-Dist: simplejson
Requires-Dist: jsonfield
Requires-Dist: rescape-python-helpers
